supabase_management/__init__.py
supabase_management/supabase_management.py
supabase_management-0.2.0.dist-info/LICENSE
supabase_management-0.2.0.dist-info/METADATA
supabase_management-0.2.0.dist-info/WHEEL
supabase_management-0.2.0.dist-info/top_level.txt
supabase_management-0.2.0.dist-info/RECORD
