Metadata-Version: 2.1
Name: supabase-management
Version: 0.2.0
Summary: A Python client for the Supabase Management API
Home-page: https://github.com/yogourt20/supabase-management-py
Author: YoGoUrT
Author-email: work@minefloat.com
Classifier: Programming Language :: Python :: 3
Classifier: License :: OSI Approved :: MIT License
Classifier: Operating System :: OS Independent
Requires-Python: >=3.7
License-File: LICENSE
Requires-Dist: httpx
